Metadata-Version: 1.1
Name: slc.smtp2zope
Version: 1.3
Summary: Provides smtp2zope integration script for slc.mailrouter.
Home-page: https://github.com/syslabcom/slc.smtp2zope
Author: Izak Burger, Syslab.com GmbH
Author-email: isburger@gmail.com
License: GPL
Keywords: smtp2zope
Platform: UNKNOWN
Classifier: Programming Language :: Python
Classifier: Framework :: Plone
